numgeo/__init__.py
numgeo/geom.py
numgeo/opt.py
numgeo/skel.py
numgeo/util.py
numgeo/vec_io.py
numgeo/scripts/__init__.py
numgeo/scripts/skel/SkeletonScript.py
numgeo/scripts/skel/__init__.py
numgeo-0.0.1a0.data/scripts/SkeletonScript.py
numgeo-0.0.1a0.dist-info/LICENSE.txt
numgeo-0.0.1a0.dist-info/METADATA
numgeo-0.0.1a0.dist-info/WHEEL
numgeo-0.0.1a0.dist-info/top_level.txt
numgeo-0.0.1a0.dist-info/RECORD
