Metadata-Version: 2.1
Name: numgeo
Version: 0.0.1a0
Summary: A geospatial package to support skeletonization
Home-page: https://github.com/eischaefer/numgeo
Author: Ethan I. Schaefer
Author-email: ethan.i.schaefer@gmail.com
License: GPL 3.0 or later
Platform: UNKNOWN
Classifier: Development Status :: 3 - Alpha
Classifier: Intended Audience :: Science/Research
Classifier: License :: OSI Approved :: GNU General Public License v3 or later (GPLv3+)
Classifier: Natural Language :: English
Classifier: Operating System :: OS Independent
Classifier: Programming Language :: Python :: 2.7
Classifier: Topic :: Scientific/Engineering :: GIS
Requires-Python: ~=2.7.3
Requires-Dist: scipy (>=0.19)
Requires-Dist: numpy (>=1.13.3)
Requires-Dist: bottleneck (>=1.2.1)
Requires-Dist: psutil (>=3.3.0)
Requires-Dist: gdal (>=2.1.3)
